MANIFEST.in
README.md
setup.py
GimmeThat.egg-info/PKG-INFO
GimmeThat.egg-info/SOURCES.txt
GimmeThat.egg-info/dependency_links.txt
GimmeThat.egg-info/not-zip-safe
GimmeThat.egg-info/requires.txt
GimmeThat.egg-info/top_level.txt
bin/gimme
bin/gimmeconf
gimmethat/__init__.py
gimmethat/__main__.py
gimmethat/antivirus.py
gimmethat/config.py
gimmethat/helpers.py
gimmethat/notifications.py
gimmethat/users.py
gimmethat/static/application.js
gimmethat/static/style.css
gimmethat/static/vue.js
gimmethat/templates/index.html
gimmethat/templates/success.html
gimmethat/templates/unauthorized.html