Metadata-Version: 1.1
Name: GimmeThat
Version: 2.0
Summary: A file transfer tool
Home-page: https://github.com/nejdetckenobi/gimme-that
Author: nejdetckenobi
Author-email: nejdetyucesoy@gmail.com
License: GPL
Platform: UNKNOWN
Classifier: License :: OSI Approved :: GNU General Public License v3 or later (GPLv3+)
Classifier: Development Status :: 4 - Beta
Classifier: Environment :: Console
Classifier: Environment :: Web Environment
Classifier: Framework :: Flask
Classifier: Intended Audience :: Developers
Classifier: Intended Audience :: System Administrators
Classifier: Intended Audience :: Other Audience
Classifier: Natural Language :: English
Classifier: Programming Language :: Python :: 3 :: Only
Classifier: Operating System :: OS Independent
Classifier: Topic :: Communications :: File Sharing
Classifier: Topic :: Utilities
